simple_eff/__init__.py
simple_eff-0.0.1a2.dist-info/WHEEL
simple_eff-0.0.1a2.dist-info/METADATA
simple_eff-0.0.1a2.dist-info/RECORD
