Metadata-Version: 2.1
Name: simple-eff
Version: 0.0.1a2
Summary: A simple tiny algebraic effects library for Python
Author: Catminusminus
Author-email: getomya@svk.jp
Requires-Python: >=3.10,<4.0
Classifier: Programming Language :: Python :: 3
Classifier: Programming Language :: Python :: 3.10
